{
  " to retrieve previous Wishlists.": ", um bereits gespeicherte Wunschlisten anzusehen.",
  " to view where we can leave your order if you are not in.": ", um anzuzeigen, wo wir Ihre Bestellung lassen können, falls Sie nicht zu Hause sind.",
  "${displayRating} out of 5 stars": "${displayRating} von 5 Sternen",
  "${openTag}Click here${closeTag} to view where we can leave your order if you are not in.": "${openTag}Klicken Sie hier${closeTag}, um anzuzeigen, wo wir Ihre Bestellung lassen können, falls Sie nicht zu Hause sind.",
  "${productDescription} as part of an outfit": "${productDescription} als Teil eines Outfits",
  "${productName} added to bag": "${productName} wurde in Ihren Warenbkorb gelegt",
  "${productName} has been removed from your bag": "${productName} wurde aus Ihrem Warenkorb entfernt",
  "${productName} has been moved to your Wishlist": "${productName} wurde zu deiner Wunschliste hinzugefügt",
  "${productName} size ${productSize} added to bag": "${productName} Größe ${productSize} wurde in Ihren Warenbkorb gelegt",
  "${remaining} characters remaining": "${remaining} Zeichen verbleibend",
  "& up": " und mehr",
  "//topshoplive.akamaized.net/ss2017/ts_unique/?dev=1&stage=1&display=mobile&l=uk": "//topshoplive.akamaized.net/ss2017/ts_unique/?display=mobile&l=de",
  "/home": "/heimat",
  "/runwaytoretail": "/de/tsde/kategorie/introducing-runway-to-retail-5843150/heimat?TS=1472547573016&intcmpid=MOBILE_LFWHUB_RUNWAYTORETAIL",
  "07123 123123": "01712 123123",
  "A 15 digit card number is required": "Eine 15-stellige Kartennummer muss eingegeben werden",
  "A 16 digit card number is required": "Eine 16-stellige Kartennummer muss eingegeben werden",
  "A 3 digit CVV is required": "Ein dreistelliger Sicherheitscode muss eingegeben werden",
  "A 4 digit CVV is required": "Ein 4-stelliger CVV-Code muss eingegeben werden",
  "3 digits required": "3 Ziffern erforderlich",
  "4 digits required": "4 Ziffern erforderlich",
  "Security Code": "Kartenprüfnummer",
  "A password is required.": "Bitte geben Sie ein Passwort ein",
  "A phone number is required": "Bitte geben Sie eine Telefonnummer ein",
  "APPLY": "ANWENDEN",
  "Add": "Alle",
  "Add All to Bag": "Alle zum Warenkorb hinzufügen",
  "Adding All to Bag": "Alles zur Tasche hinzufügen",
  "Add New Address": "Eine Neue Adresse Hinzufügen",
  "Add to bag": "In den Warenkorb legen",
  "Adding to bag" : "Hinzufügen zum beutel",
  "Add your name or change your email address": "Name hinzufügen oder E-mail-Adresse ändern",
  "Address": "Adresse",
  "Address Line 1": "Adresszeile 1",
  "Address Line 2": "Adresszeile 2",
  "Amount Charged": "Gezahlter Betrag",
  "An account with that email address already exists.": "Ein Konto mit dieser E-Mail Adresse besteht bereits.",
  "An email address is required.": "Bitte geben Sie eine E-Mail Adresse ein",
  "An error has occurred. Please try again.": "Es ist ein Fehler aufgetreten. Bitte versuchen Sie es nochmal.",
  "Apply": "Anwenden",
  "Apply card": "Karte anwenden",
  "Are you sure you want to remove ${productName} from your bag?": "Sind Sie sicher, dass Sie ${productName} aus dem Warenkorb entfernen möchten?",
  "Are you sure you want to remove all items from your bag?": "Möchten Sie wirklich alle Artikel aus Ihrem Warenkorb entfernen?",
  "BACKSTAGE": "BACKSTAGE",
  "Back to My Account": "Zurück zu Ihrem Konto",
  "Back to My Delivery & Payment Details": "Zurück zu meinen Liefer- und Zahlungsdaten",
  "Back to My Orders": "Zurück zu Ihren Bestellungen",
  "Back to My Returns": "Zurück zu deinen Rücksendungen",
  "Back to checkout": "Zurück zur Kasse",
  "Back to shopping": "Zurück zum Einkaufen",
  "Back to top": "Zurück nach oben",
  "Balance left on gift card": "Restbetrag auf der Geschenkkarte",
  "Billing": "Zahlung",
  "Billing Details": "Rechnungsdetails",
  "Billing Options": "Rechnungsoptionen",
  "Billing address": "Rechnungsadresse",
  "Billing country": "Land der Rechnungsadresse",
  "Bundle Code": "Bündelcode",
  "Buy Now": "Jetzt Kaufen",
  "BAG SUBTOTAL": "ZWISCHENSUMME DER TASCHE",
  "By placing your order you agree to our Terms & Conditions and Privacy Policy.": "Mit deiner Bestellung stimmst du unseren Allgemeinen [S][#]Geschäftsbedingungen[S] und [S][#]Datenschutzbestimmungen zu[S].",
  "CONFIRMATION DETAILS": "Bestätigungsdetails",
  "CVV": "CVV/ Sicherheitscode",
  "CVV/Security No.": "CVV/ Sicherheitscode",
  "CVV number can be found on the back of your card next to the signature": "Die Sicherheitsnummer befindet sich auf der Rückseite deiner Karte neben der Unterschrift",
  "CVV number can be found on the front of your card": "Die Sicherheitsnummer befindet sich auf der Vorderseite deiner Karte",
  "Call ${telephoneNumber}": "${telephoneNumber} Wählen",
  "Can't find country?": "Sie können Ihr Land nicht finden?",
  "Can't read your security number?": "Du kannst deine Sicherheitsnummer nicht lesen?",
  "Cancel": "Abbrechen",
  "Card ending in ${last4Digits} has expired. Try a different card or payment method": "Karte mit den Endziffern ${last4Digits} ist abgelaufen. Verwenden Sie eine andere Karte oder Zahlungsmethode",
  "Card Number": "Kartennummer",
  "Carousel Image": "Karussellbild",
  "Carrier": "Versand durch",
  "Change": "Ändern",
  "Change delivery method": "Liefermethode ändern",
  "Change my details": "Details ändern",
  "Change password again?": "Passwort nochmal ändern?",
  "Change payment details": "Zahlungsmethode ändern",
  "Change shipping destination": "Lieferadresse ändern",
  "Check out with your PayPal account": "Checkout mit deinem PayPal-Konto",
  "Check out with your IDEAL account": "Checkout mit deinem IDEAL-Konto",
  "Check out with your SOFORT account": "Checkout mit deinem SOFORT-Konto",
  "Change your account password": "Passwort für Ihr Konto ändern",
  "Check your saved delivery and payment details": "Überprüfen Sie Ihre gespeicherte Liefer- und Zahlungsdaten",
  "Check eligibility": "Zulässigkeit prüfen",
  "Checkout now": "Jetzt zur Kasse",
  "Checkout quickly without an account": "Schneller Bestellvorgang ohne Konto",
  "Choose country": "Land auswählen",
  "Choose Country Statement": "Land auswählen",
  "Choose your language": "Wähle deine Sprache",
  "Choose Your Region": "Wählen Sie Ihre Region",
  "Clear": "Löschen",
  "Clear all": "Alles löschen",
  "Clear form": "Formular löschen",
  "Click here": "Klicken Sie hier",
  "Click to select your address": "Wählen Sie ihre Adresse aus",
  "Close filters modal": "Filterauswahl schliessen",
  "Close menu": "Schliessen",
  "Close modal (can also press escape key to close).": "Modul schliessen (oder Escape zum schliessen drücken)",
  "Closed now.": "Im Moment geschlossen",
  "Closed today.": "Heute geschlossen",
  "Closing soon at": "Schliesst um",
  "Code": "Code",
  "Colour": "Farbe",
  "Confirm": "Bestätigen",
  "Confirm Password": "Passwort bestätigen",
  "Confirm email address": "E-Mail Adresse bestätigen",
  "Confirm new password": "Neues Passwort bestätigen",
  "Confirmation details": "Bestätigungsdetails",
  "Confirmation email": "Email bestätigen",
  "Contact information": "Kontaktinformationen",
  "Contact Us": "Kontaktiere uns",
  "Content is loading, please wait.": "Einen Moment bitte, Inhalt lädt.",
  "Continue": "Fortsetzen",
  "CONTINUE AS GUEST": "ALS GAST FORTFAHREN",
  "Continue Shopping": "Einkauf fortsetzen",
  "Continue shopping": "Weiter shoppen",
  "Continue to checkout": "WEITER ZUR KASSE",
  "Cookie Policy": "Cookies",
  "Could not update customer details.": "Ihre Kundendaten konnten nicht aktualisiert werden",
  "Country": "Land",
  "Create a password to manage and track your order": "Erstellen Sie ein Passwort um Ihre Bestellung zu verwalten und zu verfolgen",
  "CREATE AN ACCOUNT": "KONTO ERSTELLEN",
  "Create an account to checkout": "Erstellen Sie ein Konto, um zu bezahlen",
  "Create password": "Passwort erstellen",
  "Credited": "Gutgeschrieben",
  "Credit/Debit Card": "Kredit/Debitkarte",
  "Current password": "Aktuelles Passwort",
  "Debit and Credit Card": "Debit- und Kreditkarte",
  "DELIVERY INSTRUCTIONS": "LIEFERANWEISUNGEN",
  "Delete": "Entfernen",
  "Delivery & Returns": "Lieferung & Rücksendung",
  "Deliver to another store": "In eine andere Filiale liefern",
  "Delivery": "Lieferung",
  "Delivery Date": "Lieferdatum",
  "Delivery Details": "Lieferdetails",
  "Delivery Instructions": "Lieferanweisungen",
  "Delivery Options": "Lieferoptionen",
  "Delivery Type": "Lieferungsart",
  "Delivery Address": "Lieferadresse",
  "Delivery and returns Information": "Lieferungs- und Rücksendeinformationen",
  "Delivery and Payment": "Lieferung und Zahlung",
  "Delivery country": "Lieferland",
  "Discount": "Rabatt",
  "Display product list items in ${currentColumn} Columns": "Produktliste in ${currentColumn} Spalten anzeigen",
  "Displaying your last 20 orders. For your full order history, please contact customer service at ${customerCareNumber}.": "Für mehr Informationen über alle vorherigen Bestellungen kontaktiere bitte unseren Kundenservice - ${customerCareNumber}.",
  "Displaying your last 20 returns. For your full return history, please contact customer service at ${customerCareNumber}.": "Für mehr Informationen über alle vorherigen Retouren kontaktiere bitte unseren Kundenservice - ${customerCareNumber}.",
  "Doe": "Mustermann",
  "Double tap for large view": "Zweimal tippen zum Vergrößern",
  "E-mail me when back in stock": "Email mir wenn wieder vorrätig",
  "Edit": "Bearbeiten",
  "Eg. ***": "Beispiel: XXXXXXX",
  "Eg. 214": "Beispiel: 214",
  "Eg. W1T 3NL": "Beispiel: 10115",
  "Email": "Email",
  "Email address": "E-Mail Adresse",
  "Empty bag": "Warenkorb leeren",
  "Ending in": "Endet in",
  "Enter a password to checkout faster next time!": "Gib ein Passwort ein, um nächstes Mal schneller auszuchecken!",
  "Enter address manually": "Adresse manuell eingeben",
  "Enter New Password": "Neues Passwort eingeben",
  "Enter your CVV number to continue": "Kartenprüfnummer zum Fortfahren eingeben",
  "Enter your mobile number to receive SMS updates on your delivery.": "Geben Sie Ihre Handynummer ein, um Lieferungs-Updates per SMS zu erhalten.",
  "Enter your promotion code": "Geben Sie ihren Aktionscode ein",
  "Error": "Fehler",
  "Error with googleGeocodeService": "Es ist ein Fehler aufgetreten mit: googleGeocodeService",
  "Estimated delivery is no later than": "Vorraussichtliche Lieferung erfolgt spätestens am",
  "Example: Doe": "Beispiel: Mustermann",
  "Example: John": "Beispiel: Erika",
  "Example: XXX": "Beispiel: XXX",
  "Example: XXXX": "Beispiel: XXXX",
  "Example: XXXXXXX": "Beispiel: XXXXXXX",
  "Expires on": "Läuft aus am",
  "Expiry Date": "Ablaufdatum",
  "Expiry: month": "Monat",
  "Expiry: year": "Jahr",
  "FIND ADDRESS": "Adresse finden",
  "Filter": "Verfeinern",
  "Find Address": "Adresse finden",
  "Find a store": "Filiale suchen",
  "Find in store": "Filiale suchen",
  "Find out more": "Mehr erfahren",
  "Find UK Stores": "UK Stores finden",
  "First Name": "Vorname",
  "Follow Us": "Auf Social Media folgen",
  "Follow us": "Uns Folgen",
  "For American Express card holders it can be found on the front.": "Auf American-Express-Karten befindet sich die Sicherheitsnummer auf der Vorderseite der Karte.",
  "For international customers, please call ${numbers[brandCode]['intl']}.": "Für internationale Kunden, bitte ${numbers[brandCode]['intl']} anrufen.",
  "Forgot your password?": "Passwort vergessen?",
  "Forgotten your password?": "Passwort vergessen?",
  "Free": "Kostenlos",
  "free shipping": "eine kostenlose Lieferung",
  "From": "Ab",
  "GO TO CHECKOUT": "ZUR KASSE GEHEN",
  "Get another link": "Neuen Link senden",
  "Get Directions": "Routenplaner",
  "Get my current location": "Meinen aktuellen Standort anzeigen",
  "Get your goods today and pay 3 months later": "Zahle bequem innerhalb von 14 Tagen",
  "Gift card": "Gutscheinkarte",
  "Gift Card": "Gutscheinkarte",
  "Gift Card Number": "Geschenkkartennummer",
  "Gift card number": "Geschenkkartennummer",
  "Giftcard PIN needs to be 4 characters long.": "Geschenkkarten-PIN muss 4 Stellen haben",
  "Giftcard number needs to be 16 characters long.": "Geschenkkartennummer muss 16 Stellen haben",
  "You can use gift cards to pay for up to ${giftCardRedemptionPercentage}% of each order. Any balance will remain on your gift card for future purchases.": "Mit Geschenkkarten können Sie bis zu ${giftCardRedemptionPercentage}% jeder Bestellung bezahlen. Der Restbetrag verbleibt für zukünftige Einkäufe auf Ihrer Geschenkkarte.",
  "Go": "Los",
  "Go back": "Zurück",
  "Go to Checkout": "JETZT ZUR KASSE",
  "Go to checkout": "Zur Kasse gehen",
  "Guest Customer": "Gastkunde",
  "Hair, make-up, final touches to the styling… there’s a lot that goes into making the Topshop Unique show look this good. Add us @topshop_snaps to get an insider look at the backstage action.": "Haare, Make-Up, letzte Schliffe beim Styling... es passiert viel damit die Topshop Unique Show gut aussieht. Folge uns auf @topshop_snaps um hinter die Kulissen zu blicken.",
  "Help & Information": "Hilfe & FAQs",
  "Hide": "Verbergen",
  "Home": "Home",
  "House name or number": "Hausname oder Nummer",
  "House number": "Hausnummer",
  "How to find your security number": "So findest du die Sicherheitsnummer",
  "I accept the": "Ich akzeptiere die",
  "I'm looking for a store in": "Ich suche einen Laden in",
  "If you can't read your security number, please contact your card issuer": "Wenn du deine Sicherheitsnummer nicht lesen kannst, kontaktiere  bitte den Kartenaussteller.",
  "If you have entered a valid email address, you should receive a password reset email shortly.":"Falls du eine uns bekannte E-Mail Adresse angegeben hast, solltest du in Kürze eine Email zum Zurücksetzen des Passwortes erhalten. Keine Mail erhalten?",
  "Wenn du eine gültige E-Mail-Adresse angegeben hast, solltest du in Kürze eine E-Mail zum Zurücksetzen deines Passworts erhalten.":"Falls du eine uns bekannte E-Mail Adresse angegeben hast, solltest du in Kürze eine Email zum Zurücksetzen des Passwortes erhalten. Keine Mail erhalten?",
  "If you have entered an email address that we recognise, you should receive a password reset email shortly. Any problems getting your email?": "Falls du eine uns bekannte E-Mail Adresse angegeben hast, solltest du in Kürze eine Email zum Zurücksetzen des Passwortes erhalten. Keine Mail erhalten?",
  "Image carousel, press Enter to cycle through the images, press the Z key to zoom in and out of an image. Once zoomed in, use WASD keys to pan around image.": "Bildergalerie, klicke Enter um durch die Bilder zu navigieren, klicke die Z-Taste um ein und aus zu zoomen. Sobald gezoomt ist, nutze die WASD-Tasten um das Bild zu schwenken.",
  "In Stock": "Auf Lager",
  "International Store Finder": "Internationaler Store Finder",
  "item": "Artikel",
  "items": "Artikel",
  "Item code": "Artikelnummer",
  "Please note stock moves quickly and we cannot guarantee availability.": "Der Lagerbestand ändert sich schnell und wir können keine Verfügbarkeit garantieren.",
  "Item discount": "Artikelrabatt",
  "Item price": "Preis",
  "item(s) added to bag": "Artikel zum Einkauf hinzugefügt",
  "John": "Max",
  "Klarna": "Klarna",
  "Last Name": "Nachname",
  "Left arrow": "Linker Pfeil",
  "Let us know where we can leave your order if you are not in.": "Sagen Sie uns wo wir ihre Bestellung lassen können falls Sie nicht zuhause sind.",
  "link expires in one hour": "Der Link läuft in einer Stunde ab und kann nur einmal verwendet werden. Überprüfen Sie daher Ihre E-Mails in den nächsten Minuten.",
  "link no longer valid": "Dieser Link zum Zurücksetzen des Passworts ist nicht mehr gültig. Wenn Sie Ihr Passwort immer noch zurücksetzen müssen, fordern Sie unten ein weiteres Zurücksetzen an.",
  "Loading": "Lädt...",
  "Login": "Anmelden",
  "Log in": "Einloggen",
  "Log off": "Abmelden",
  "Looks like you currently have an active subscription. You can only purchase and have one active subscription at any one time.": "Looks like you currently have an active subscription. You can only purchase and have one active subscription at any one time.",
  "Low stock": "Niedrige Lagerbestände",
  "manage cookies": "cookies verwalten",
  "MOBILE NUMBER": "Handynummer",
  "MY ACCOUNT": "Mein Konto",
  "Manage your email preferences": "Verwaltung Ihrer E-Mail-Einstellungen",
  "Max. 30 characters": "Max. 30 Zeichen",
  "Max. ${maxCharacters} characters": "Max. ${maxCharacters} Zeichen",
  "Max. 30 characters ${remaining} remaining": "Max. 30 Zeichen ${remaining} übrig",
  "Mobile": "Handy",
  "Mobile Number": "Handynummer",
  "Monday to Friday": "Montag bis Freitag",
  "Move to Wishlist": "Zur Wunschliste hinzufügen",
  "Moving to Wishlist": "Zur Wunschliste hinzufügen",
  "My Order": "Meine Bestellung",
  "My account": "Mein Konto",
  "My Bag": "Mein Warenkorb",
  "My Delivery & Payment Details": "Meine Liefer- und Zahlungsdaten",
  "My delivery address is the same as my billing address": "Meine Lieferadresse ist auch meine Rechnungsadresse",
  "My details": "Meine Details",
  "My orders": "Meine Bestellungen",
  "My returns": "Meine Retouren",
  "My Returns": "Meine Retouren",
  "My password": "Mein Passwort",
  "My Preferences": "Meine E-Mail-Einstellungen",
  "My Wishlist": "Meine Wunschliste",
  "New Customer": "Neuer Kunde",
  "New Customer?": "Neuer Kunde?",
  "New password": "Neues Passwort",
  "Next": "Weiter",
  "Not available at this store": "Leider nicht in dieser Filiale verfügbar",
  "Not working?": "Funktioniert nicht?",
  "Notify me when available": "Benachrichtige mich wenn wieder verfügbar",
  "Now": "Jetzt",
  "Ok": "Ok",
  "or": "oder",
  "On the Blog": "Auf dem Blog",
  "One Column": "Eine Spalte",
  "Only digits allowed": "Bitte geben Sie nur Ziffern ein",
  "Only ${quantity} left in stock": "Schnell! Nur noch ${quantity} Artikel auf Lager",
  "Only ${inventory} available": "Nur noch ${inventory} verfügbar",
  "Open categories menu": "Kategoriemenü öffnen",
  "Open search bar to search for products": "Suchleiste öffnen um nach Produkten zu suchen",
  "Open to the public from 3pm, this market stall will sell pieces from the collection straight after the show.": "In diesem Stand werden wir Teile direkt vom Laufsteg verkaufen und er ist ab 16:00 Uhr offen für Jeden.",
  "Open today until": "Heute geöffnet bis",
  "Opening hours": "Öffnungszeiten",
  "Opens today at": "Heute geöffnet ab",
  "Opens tomorrow at": "Morgen geöffnet ab",
  "Or ": "Oder ",
  "or manually enter address": "oder adresse manuell eingeben",
  "Order Number": "Bestellnummer",
  "Order Summary and Confirmation": "Bestellübersicht und Bestätigung",
  "Order and Pay Now": "Jetzt kaufen",
  "Order Total": "Auftragssumme",
  "Order details": "Bestellungsdetails",
  "Order date": "Bestelldatum",
  "Order not found": "Bestellung nicht gefunden",
  "Order summary": "Warenkorb ansehen",
  "Order status": "Versandstatus",
  "Out of stock": "Nicht vorrätig",
  "Outfit View": "Outfit anzeigen",
  "PAYMENT DETAILS": "Zahlungsdetails",
  "Payment Details": "Zahlungsdetails",
  "Payment method": "Zahlungsmethode",
  "PIN": "PIN Nummer",
  "Password": "Passwort",
  "Password cannot be your email": "Passwort darf nicht Ihre E-Mail Adresse sein",
  "Passwords must have at least six characters including one digit.": "Passwörter sollten mindestens 6 Buchstaben lang sein und 1 Nummer enthalten",
  "Pay in 30 days or pay in 3 interest-free instalments. No fees.": "Bezahle in 30 Tagen oder in 3 zinslosen Raten. Keine Gebühren.",
  "Pay with Apple Pay": "Bezahlen mit Apple Pay",
  "Pay via PayPal": "Mit PayPal bezahlen",
  "Pay with Klarna": "Mit Klarna bezahlen",
  "Payment": "Zahlung",
  "Payment details": "Zahlungsdetails",
  "Payment type": "Zahlungsart",
  "play video": "Video abspielen",
  "Please allow 7 days from the date above before contacting Customer Services regarding your refund.": "Bei Rückfragen, warte bitte bis zu 7 Tage von dem oben angegebenen Rückgabedatum bevor du unseren Kundenservice kontaktierst.",
  "Please choose your shipping destination": "Bitte wählen Sie Ihr Lieferziel",
  "Please click on FIND ADDRESS": "Bitte ADRESSE FINDEN klicken",
  "Please collect within 10 days": "Bitte innerhalb von 10 Tagen abholen",
  "Please confirm this new address or cancel to continue":"Bitte bestätige diese neue Adresse oder beende den Vorgang um fortzufahren",
  "Please ensure that both passwords match": "Bitte stellen Sie sicher, dass beide Passwörter übereinstimmen",
  "Please ensure that both passwords match.": "Bitte beachten Sie, dass beide Passwörter übereinstimmen",
  "Please ensure that your password does not contain your email address.": "Bitte beachten Sie, dass Ihr Passwort Ihre Email-Addresse nicht enthält",
  "Please enter a password that is at least 6 characters long and includes a number": "Bitte gib ein Passwort ein, das mindestens aus 6 Zeichen und einer Zahl besteht",
  "Please enter a password less than 20 characters": "Bitte geben Sie ein Passwort mit weniger als 20 Zeichen ein",
  "Please enter a password of at least 6 characters": "Bitte geben Sie ein Passwort mit mindestens 6 Zeichen ein",
  "Please enter a valid email address.": "Bitte geben Sie eine gültige E-Mail Adresse ein",
  "Please enter a valid gift card number": "Bitte geben Sie eine gültige Gechenkkartennummer ein",
  "Please enter a valid phone number": "Bitte geben Sie eine gültige Telefonnummer ein",
  "Please enter a valid post code": "Bitte geben Sie eine gültige PLZ ein",
  "Please enter your password or try another email address.": "Bitte melde dich an oder versuche eine andere E-Mail Adresse.",
  "Please note, for security reasons you will need to update your payment details each time you update your delivery information.": "Bitte beachten Sie, dass Sie aus Sicherheitsgründen Ihre Zahlungsdetails aktualisieren müssen wenn Sie Ihre Lieferinformationen ändern.",
  "PLEASE NOTE: If you have items in your basket they will be transferred, but will be subject to local pricing and promotions. Some items may not be suitable for sale in your selected region and will be removed.": "Die Artikel in deinem Warenkorb werden übertragen, gemäß lokaler Preise und Promotionen. In deiner Region nicht käufliche Artikel werden aus dem Warenkorb entfernt.",
  "Please note, you can update your billing details when you check out.": "Bitte beachten Sie, dass Sie Ihre Rechnungsdetails im Checkout aktualisieren können",
  "Please provide your login details or try an other email address": "Bitte melden Sie sich an oder versuchen Sie eine andere E-Mail Adresse.",
  "Please review your bag.": "Bitte überprüfen Sie Ihre tasche.",
  "Please select": "Bitte auswählen",
  "Please select a delivery location before you proceed": "Bitte wählen Sie eine Lieferadresse, um fortzufahren.",
  "Please select a nominated delivery date:": "Bitte wählen Sie ein Lieferdatum",
  "Please select a valid expiry date": "Bitte geben Sie ein gültiges Ablaufdatum an",
  "Please select your address...": "Bitte wählen Sie eine Adresse von der folgenden Liste",
  "Please select your country": "Bitte Land auswählen",
  "Please select your size to continue": "Bitte gib deine Größe an, um fortzufahren",
  "Please sign me up for emails": "Für wöchentliche Emails anmelden",
  "Please edit or remove": "Bitte bearbeiten oder entfernen",
  "Postal Code": "Postleitzahl",
  "Postal Index Number": "Postleitzahl",
  "Postcode": "PLZ",
  "Previous": "Vorherig",
  "Price": "Preis",
  "Primary Phone Number": "Telefonnummer",
  "Phone Number": "Telefonnummer",
  "Privacy & Cookie Policy": "Datenschutz & Cookies",
  "Privacy Policy": "Datenschutz",
  "Proceed": "Weiter",
  "Proceed to Payment": "Weiter zur Bezahlung",
  "Product Code": "Produkt Code",
  "Product details": "Produktinfo",
  "Product View": "Produkt anzeigen",
  "Product information loading": "Produktinformation lädt",
  "Product is out of stock": "Das Produkt ist nicht auf Lager",
  "Promotions & Gift Cards": "Geschenkkarten & Angebote",
  "Promo & Student Codes": "Promo Codes und Studentenrabatt",
  "Promotion Code or Discount": "Rabattcode oder Discount",
  "Promotion Code or Student discount": "Rabattcode oder Studentenrabatt",
  "Promotion or Student Discount": "Promotion oder Studentenrabatt",
  "Provide us with your email address and we’ll let you know when the item becomes available.": "Geben Sie Ihre E-Mail Adresse ein und wir sagen Ihnen Bescheid, sobald der Artikel vorrätig ist",
  "Provide us with your email address and we’ll let you know when this item arrives on": "Geben Sie Ihre E-Mail Adresse ein und wir sagen Ihnen Bescheid, wann der Artikel vorrätig sein wird",
  "Quantity": "Anzahl",
  "Qty": "Anz.",
  "Read More": "Meh lesen",
  "REVIEW ORDER AND CONFIRM": "Bestellung ansehen & bestätigen",
  "RRP": "UVP",
  "Read reviews": "Bewertungen lesen",
  "Recently viewed": "Zuletzt angesehen",
  "Register": "Registrieren",
  "Register and Pay Now": "Jetzt registrieren und bezahlen",
  "Register and Pay via PayPal": "Jetzt registrieren und mit PayPal bezahlen",
  "Register and Pay Later": "Zahlung per Klarna Rechnung",
  "Reload": "Erneut laden",
  "Remember me": "Daten merken",
  "Remove": "Entfernen",
  "Removed": "Entfernt",
  "Remove this gift card": "Geschenkkarte entfernen",
  "Reset Form": "Zurücksetzen",
  "Reset link expired or not valid": "Link zum Zurücksetzen abgelaufen oder ungültig",
  "Reset password": "Passwort erneuern",
  "Returns": "Rücksendung",
  "Return Details": "Rückgabe Details",
  "Returning Customer": "Registrierter Kunde",
  "Review order and confirm": "Bestellung ansehen & bestätigen",
  "SAVE CHANGES": "Änderungen speichern",
  "Save New Password": "Neues Passwort speichern",
  "Save email address": "Email-Adresse speichern",
  "Same as delivery address": "Meine Lieferadresse ist die gleiche wie meine Rechnungsadresse",
  "Saturday": "Samstag",
  "Save": "Speichern",
  "Save for later": "Für später merken",
  "Save payment details for future purchases?": "Kartendaten für zukünftige Einkäufe speichern?",
  "Search": "Suche",
  "Search - ${categoryTitle}": "${categoryTitle} suchen",
  "Search again": "Erneut suchen",
  "Search for a product...": "z.B. Jeans suchen",
  "Search for store...": "Filiale finden",
  "Search, e.g. denim jacket": "Suchen, z.B. Jeansjacke",
  "Secure Checkout": "Sicher Bezahlen",
  "See More": "Mehr anzeigen",
  "See Prev": "Zurückgehen",
  "See full details": "Vollständige Details ansehen",
  "Select": "Auswählen",
  "Select a size": "Größe auswählen",
  "Select country": "Land auswählen",
  "Select language": "Wähle deine Sprache",
  "Select size": "Größe auswählen",
  "Select store": "Filiale auswählen",
  "Select the ${WISHLIST_ICON} icon next to our products to save them to your Wishlist.": "Mit dem ${WISHLIST_ICON}-Symbol neben einem Produkt kannst du es zu deiner Wunschliste hinzufügen.",
  "Select your items": "Wähle deine Artikel",
  "Select your preferred delivery option": "Wählen Sie ihre bevorzugte Lieferoption",
  "Send Password Reset Email": "E-Mail zum Zurücksetzen des Passworts senden",
  "Session Expired": "Session Expired",
  "Ship to": "Verschicken nach",
  "SHIPPING": "VERSCHIFFUNG",
  "Shipping to": "Verschicken nach",
  "Shop By Category": "Kategorien shoppen",
  "Shop it before it's gone": "Kaufe es, bevor es vergriffen ist",
  "Shop now, Pay later": "Shoppe jetzt, Bezahle später",
  "Shop the set": "Den look shoppen",
  "Shop securely with us": "Sicher einkaufen",
  "Show": "Zeigen",
  "Show more": "Mehr anzeigen ...",
  "Sign In": "Anmelden",
  "Sign in to checkout": "Melden Sie sich an, um schneller zu bezahlen",
  "Sign In to My Account or Proceed as Guest": "In meinen Account einloggen oder als Gast fortfahren",
  "Sign Up for news straight to your inbox": "MELDE DICH FÜR DEN NEWSLETTER AN",
  "Sign in or Register": "Anmelden Oder Registrieren",
  "Sign in to save products to your Wishlist": "Melde dich an, um Produkte zu deiner Wunschliste hinzuzufügen.",
  "Sign in again to pick up where you left off": "Logge dich ein, um zum letzten Schritt zurückzukehren",
  "Sign out": "Abmelden",
  "Similar product recommendations, press the S key to stop automatic cycling. Press D to cycle forwards through the products, or A to cycle backwards": "Ähnliche Produktempfehlungen, drücke die S-Taste um den automatischen Zyklus zu stoppen. Drücke D um nach vorne durch die Produkte zu klicken, oder A für rückwärts",
  "Size": "Größe",
  "size": "größe",
  "Size guide": "Größentabelle",
  "Skip to content": "Zu den Inhalten gehen",
  "Some items are no longer available.": "Einige Artikel sind nicht mehr verfügbar.",
  "Sorry your search didn’t match any products.": "Wir konnten leider keine Übereinstimmung für Ihre Suche finden",
  "Sorry, there's been an error with loading the page. Please try again later": "Es tut uns leid, die Seite konnte leider nicht geladen werden. Bitte versuchen Sie es später nochmal",
  "Sorry, this item is out of stock": "Sorry, dieser Artikel ist ausverkauft",
  "Sorry, we couldn't find any locations matching your search. Please enter another location and try again.": "Die Suche ergab keine passende Standorte. Bitte geben Sie einen anderen Standort ein und versuchen Sie nochmal.",
  "Sort product list by": "Produktliste sortieren nach",
  "Standard Delivery": "\u20ACnderungen speichern",
  "State": "Bundesland",
  "Status": "Status",
  "stop video": "Video stoppen",
  "Store Locator": "Filialsuche",
  "Street Address": "Strasse",
  "Submit": "Abschicken",
  "Submitted": "Abgeschickt",
  "Submitting": "Wird abgeschickt",
  "Subtotal": "Zwischensumme",
  "Subtotal before Delivery": "Zwischensumme",
  "Summary": "Zusammenfassung",
  "Sunday": "Sonntag",
  "Surname": "Nachname",
  "THE MARKET": "DER MARKT",
  "THE RUNWAY": "DER LAUFSTEG",
  "TOPSHOP UNIQUE SHOP": "TOPSHOP UNIQUE SHOP",
  "TOPSHOP UNIQUE SHOW STARTS IN": "Topshop Unique Show beginnt in",
  "Terms & Conditions": "AGBs",
  "Thank You": "Danke",
  "Thank You For Your Order": "Vielen dank für Ihre Bestellung",
  "Thank you for submitting your details.": "Danke für Ihre Details",
  "Thank you for updating your details.": "Danke, dass Sie Ihre Details aktualisiert haben",
  "Thank you, your gift card has been added.": "Vielen Dank, Ihre Geschenkkarte wurde hinzugefügt",
  "The buy now, pay later payment option is not available for this order. Please select an alternative payment option.": "Klarna Rechnung ist nicht verfügbar für diese Bestellung. Bitte wähle eine alternative Zahlungsmethode aus.",
  "The catwalk runs directly through Spitafield’s market – with room to house over 700 fashion editors and celebrities on the front row. Want to watch too? You can tune in to the livestream at 2pm BST.": "Der Laufsteg geht direkt durch den Old Spitalfields Markt – mit Platz für über 700 Redakteure und Stars in der Front Row. Du willst auch zusehen? Schalte um 15.00 Uhr den Livestream ein.",
  "The promotion code you have entered has not been recognised. Please confirm the code and try again.": "Der eingegebene Promotioncode ist ungültig. Bitte überprüfen Sie den Code und versuchen Sie es nochmal.",
  "The security number (CVV) is the number that can be found at the back of your card next to the signature.": "Die Sicherheitsnummer ist die dreistellige Zahl auf der Rückseite der Karte neben der Unterschrift",
  "There are no additional delivery options available": "Es sind keine weiteren Lieferoptionen auswählbar",
  "There was an error submitting the form. Please try again.": "Leider ist ein Fehler aufgetreten. Bitte versuchen Sie es nochmal",
  "There were no orders found": "Es wurden keine Bestellungen gefunden",
  "There are no returns found": "Es wurden keine Retouren gefunden",
  "There are no products matching your current search criteria.": "Es sind keine zur Auswahl passenden Produkte vorhanden",
  "There's been a temporary issue. Please confirm your order again.": "Es gab ein vorrübergehendes Problem. Bitte geben Sie Ihre Bestellung erneut auf.",
  "This field is required": "Dieses Feld ist erforderlich",
  "This is the filters modal. Select any required filters and press apply to return to a filtered product list.": "Das ist das Filtermodul. Wählen Sie beliebige Filter und klicken Sie 'Anwenden' um die gefilterten Produkte anzuzeigen",
  "This is the product page for: ${name}": "Das ist die Produktseite für ${name}",
  "This is the quick product view page for: ${name}": "Dies ist die Produktseite für: ${name}",
  "This style is selling fast!": "Dieser Style verkauft sich schnell!",
  "This password reset link is no longer valid. If you still need to reset your password, request another reset below. The link will expire in one hour, and can be used only once, so please check your email in the next few minutes.": "Der Link zum Zurücksetzen des Passwortes ist nicht mehr gültig. Falls du dein Passwort immer noch zurücksetzen willst, sende unten eine erneute Anfrage. Der Link ist nur eine Stunde gültig und kann nur einmal verwendet werden, also checke deine Mails in den nächsten paar Minuten.",
  "Three Columns": "Drei Spalten",
  "Title": "Titel",
  "Tick here to receive style inspiration and exclusives straight to your inbox.": "Klicke hier, um Style Inspiration und exklusive Inhalte direkt in dein Postfach zu erhalten.",
  "To add a new address, delete one from the list." : "Löschen aie eine neue adresse aus der liste, um sie hinzuzufügen.",
  "Total": "Gesamt",
  "Total to pay": "Insgesamt zu bezahlen",
  "Total left to pay": "Noch zu zahlender Betrag",
  "Total Cost": "Gesamtbetrag",
  "Total credited": "Gesamtgutschrift",
  "Total discount": "Gesamtrabatt",
  "Total credit returned": "Gesamtgutschrift",
  "Town or Locality": "Bezirk oder Ortschaft",
  "Town/City": "Ort/ Stadt",
  "Track My Order": "Meine Bestellung verfolgen",
  "Track my order": "Meine Bestellung verfolgen",
  "Track your current orders, view your order history and start a return": "Verfolgen Sie Ihre aktuellen Bestellungen, zeigen Sie Ihre Bestellhistorie an und starten Sie eine Rücksendung",
  "Track your current returns and view your return history": "Verfolge aktuelle Retouren, frühere Retouren ansehen",
  "Tracking number": "Trackingnummer",
  "Trending Product": "Trendige Produkte",
  "Try another email address": "Versuchen Sie eine andere Email-Adresse",
  "Try before you buy": "Klarna Rechnung",
  "Try clearing some filters to view more results": "Filter zurücksetzen um mehr Ergebnisse zu sehen",
  "Try using fewer words and make sure all words are spelled correctly.": "Versuche weniger Worte zu verwenden und gehe sicher, dass alles richtig geschrieben ist.",
  "Two Columns": "Zwei Spalten",
  "UNDO LAST SELECTION": "LETZTE AUSWAHL RÜCKGÄNGIG MACHEN",
  "Unable to find order, please check your account": "Bestellung konnte leider nicht gefunden werden. Bitte überprüfen Sie Ihre Konto",
  "Unfortunately your session has timed out.": "Ihre Sitzung ist leider abgelaufen",
  "Unfortunately we could not process your payment. An error may have occurred with your provider or you may have chosen to cancel the payment. No money has been taken from your card and the transaction has been cancelled. If you would like to continue your purchase please try again.": "Leider konnte deine Zahlung nicht verarbeitet werden. Es ist warscheinlich ein Fehler mit deinem Anbieter aufgetreten, oder die Zahlung wurde abgebrochen. Deine Karte wurde nicht belastet und die Transaktion wurde abgebrochen. Falls du den Kauf fortsetzen möchtest, versuche es bitte noch einmal.",
  "Unfortunately, we were unable to load the map.": "Leider konnten wir die Karte nicht laden.",
  "Update details": "Details aktualisieren",
  "Use for Billing Address": "Als Rechnungsadresse benutzen",
  "Use our quick checkout process": "Nutzen Sie jetzt unseren schnellen Checkout",
  "VERIFY": "Prüfen",
  "View bag": "Warenkorb ansehen",
  "View in maps": "Zur Karte",
  "View next image": "Nächstes Bild ansehen",
  "View previous image": "Vorheriges Bild ansehen",
  "View product information": "Produktinformationen ansehen",
  "View profile": "Konto ansehen",
  "View shopping cart": "Warenkorb ansehen",
  "View The Set": "Set ansehen",
  "Was": "War",
  "We are unable to accept a zero value order": "We are unable to accept a zero value order",
  "We accept": "Zahlungsarten",
  "We are unable to find your address at the moment. Please enter your address manually.": "Wir können Ihre Adresse im Moment nicht finden. Bitte geben Sie Ihre Adresse manuell ein.",
  "We ship to over 100 countries": "Wir liefern in über 100 Länder",
  "We’ve curated exclusive market stalls open to all. Get your jeans customised, shop catwalk beauty looks and more…": "Unsere exklusiven Marktstände sind offen für alle. Lasse deine Jeans personalisieren, shoppe Laufsteg-Beauty und mehr...",
  "We'll only call you if there are issues with your order": "Wir rufen Sie nur an, wenn bei Ihrer Bestellung ein Problem auftritt",
  "Welcome back": "Willkommen zurück",
  "We recommend choosing a password that you haven't used for another online account": "Wir empfehlen, ein Passwort zu wählen, das noch nicht für ein anderes Online-Konto verwendet wurde",
  "What's a CVV?": "CVV/ Sicherheitsnummer",
  "What's this?": "Was ist das?",
  "Which size are you looking for?": "Nach welcher Größe suchen Sie?",
  "Why not try?": "Wir empfehlen",
  "Wishlist": "Wunschliste",
  "You also consent to some of your data being stored by ${brandName}, which may be used to make future shopping experiences better for you.": "Du erklärst Dich außerdem einverstanden, dass einige Deiner Daten von ${brandName} gespeichert werden, Diese können dafür verwendet werden, um Dein Einkaufserlebnis in Zukunft noch besser zu gestalten.",
  "You are about to be taken to the website for": "Du landest in Kürze auf der Website für",
  "You can create an account later if you wish": "Sie können ihr Konto auch später erstellen",
  "You can only save 4 addresses.": "Sie können nur 4 adressen speichern.",
  "You have items in your basket from a previous visit": "Sie haben Artikel von einem früheren Besuch in Ihrem Warenkorb.",
  "You have added the maximum number of gift cards for this order.": "Sie haben die maximale Anzahl and Geschenkkarten für diese Bestellung hinzugefügt",
  "You have items in your bag that are no longer available. Please review your bag before payment.": "Sie haben Artikel in ihrem Warenkorb die leider nicht mehr verfügbar sind. Bitte überprüfen Sie ihren Warenkorb bevor Sie fortfahren",
  "You have items in your shopping bag from a previous visit.": "Sie haben Artikel von einem vorigen Besuch in Ihrem Warenkorb.",
  "You have items in your shopping bag from a previous visit. Please review the items in your bag before continuing to payment.": "Sie haben Artikel von einem vorigen Besuch in Ihrem Warenkorb. Bitte überprüfen Sie den Inhalt Ihres Warenkorbs, bevor Sie mit Ihrer Zahlung fortfahren",
  "You have out of stock item(s) in your bag. Please remove them before you continue your checkout.": "Sie haben Artikel in ihrem Warenkorb die leider nicht mehr verfügbar sind. Bitte entfernen Sie diese bevor Sie fortfahren",
  "You must accept the Terms and Conditions.": "Sie müssen den AGBs zustimmen",
  "You successfully logged in with ${email}": "Du hast dich erfolgreich mit ${email} eingeloggt",
  "You will be asked to log onto ${selectedAPMLabel} to confirm your order": "Du wirst aufgefordert, dich bei ${selectedAPMLabel} anzumelden um deine Bestellung zu bestätigen.",
  "You'll get an order confirmation email shortly.": "Du erhälst in Kürze eine Bestellbestätigung per E-mail.",
  "You'll get an order confirmation email shortly to": "Du erhälst in Kürze eine Bestellbestätigung per E-mail an",
  "You'll have a chance to review your order and check your delivery & billing information on the next screen before ordering.": "Sie können ihre Bestellung und Adresseingaben im nächsten Schritt nochmals überprüfen",
  "You'll have a chance to review your order, add promotion codes, and check your delivery & billing information on the next screen before ordering.": "Im nächsten Schritt können Sie Promotioncodes hinzufügen sowie Ihre Bestellung und Adresseingaben nochmals überprüfen.",
  "You will be asked to log onto ${label} to confirm your next order": "Bei einer nächsten Bestellung wirst du aufgefordert dich bei ${label} anzumelden",
  "You’ve been inactive for a while": "Du bist seit einer Weile inaktiv",
  "Your changes have been saved": "Deine Änderungen wurden gespeichert",
  "Your Delivery Details": "Ihre Lieferdetails",
  "Your delivery subscription expires on": "Your delivery subscription expires on",
  "Your Details": "Ihre Details",
  "Your order": "Deine Bestellung",
  "Your Order is Complete": "Ihre Bestellung wurde erhalten",
  "Your Order is now complete. Redirecting to your Order History ...": "Ihre Bestellung ist jetzt vollständig. Sie werden zu Ihren Bestellungen zurückgeleitet",
  "Your order will be delivered by": "Lieferung spätestens zum",
  "Your order will be delivered on": "Lieferung spätestens zum",
  "Your bag": "Ihr Warenkorb",
  "Your bag qualifies for": "Dein Einkauf qualifiziert sich für",
  "Your billing address is the address at which the card you are paying with is registered to. Please enter this as it appears on your bank or credit card statement.": "Ihre Rechnungsadresse ist die Adresse auf die ihre Karte registriert ist. Bitte geben sie diese an wie sie auf ihrem Bank - oder Kreditkartenauszug erscheint.",
  "Your item has been added to your bag": "Der Artikel wurde in Ihren Warenkorb gelegt",
  "Your new password can't be the same as your previous password.": "Ihr neues Passwort darf nicht mit dem alten identisch sein.",
  "Your order will arrive": "Ihre Bestellung wird verschickt",
  "Your order will arrive by": "Deine Bestellung wird vor dem .... ankommen",
  "Your order will be delivered to": "Ihre Bestellung wird geliefert an",
  "Your password has been successfully changed.": "Ihr Passwort wurde erfolgreich geändert",
  "Your payment type has expired. Please update your payment details from the 'Change' option above.": "Diese Zahlungsart ist leider abgelaufen. Bitte änderen Sie Ihre Zahlungsinformationen in der Änderungsoption oben.",
  "Your profile details have been successfully updated.": "Ihre Details wurden erfolgreich aktualisiert",
  "Your promo code has been applied": "Dein Rabattcode wurde angewendet",
  "Your search did not return any results": "Deine suche hat keine treffer ergeben",
  "YOUR SEARCH DID NOT RETURN ANY RESULTS": "DEINE SUCHE HAT KEINE TREFFER ERGEBEN",
  "Your shopping bag is currently empty.": "Ihr Warenkorb ist leer",
  "Your subscription has expired": "Your subscription has expired",
  "Zip Code": "Postleitzahl",
  "category": "kategorie",
  "Category": "Kategorie",
  "change-your-shipping-destination": "lieferadresse-ändern",
  "clear filters": "Filter entfernen",
  "example@domain.com": "beispiel@domain.com",
  "friday": "Freitag",
  "homepage": "Startseite",
  "http://insideout.topshop.com/2016/08/topshop-uniques-new-home-old-spitalfields-market": "http://insideout.topshop.com/2016/09/topshops-spitalfields-market-stalls-at-london-fashion-week",
  "including delivery": "inklusive Lieferung",
  "kilometres": "Kilometer",
  "left": "vorherige",
  "loading products": "Lädt Artikel",
  "Logout": "Ausloggen",
  "logout worked but the api sent back errors": "Logout war erfolgreich aber die API ergab eine Fehlermeldung",
  "miles": "Meilen",
  "monday": "Montag",
  "my-account": "mein-konto",
  "outfit": "Outfit",
  "product": "produkt",
  "RENEW": "RENEW",
  "results": "Resultate",
  "right": "Nächste",
  "sign-in-or-register": "anmelden-oder-registrieren",
  "stars": "Sterne",
  "tcs": "agbs",
  "thursday": "Donnerstag",
  "tuesday": "Dienstag",
  "wednesday": "Mittwoch",
  "| secs| mins| hours| days| weeks| months| years|||": "| seks| mins| stunden| tage| woche| monate| jahre|||",
  "| sec| min| hour| day| week| month| year|||": "| sek| min| stunde| tag| woche| monat| jahr|||",
  "One sized item": "Einheitsgröße",
  "Please remove all emoji characters": "Bitte alle Emoji Schriftzeichen entfernen",
  "Your order will be delivered no later than": "Lieferung bis spätestens",
  "We're sorry, an error has occurred. We're working to fix it as soon as possible.": "Entschuldigung, ein Fehler ist aufgetreten. Wir arbeiten daran, das Problem so schnell wie möglich zu beheben.",
  "you may also like": "Das könnte dir auch gefallen",
  "you might also like": "Das könnte dir auch gefallen",
  "Delivery method": "Versandart",
  "You are viewing the website for ${currentSite}. Would you like to view the website for ${otherSite} instead?": "Du bist auf der Website für ${currentSite}. Möchtest du die Seite ${otherSite} ansehen?",
  "Take me to the ${otherSite} site": "Bring mich zur ${otherSite} Seite",
  "Continue to the ${currentSite} site": "Weiter zur ${currentSite} Seite",
  "NOTE: If you choose to be redirected, you will be taken to the home page.": "Wenn du wählst umgeleitet zu werden, wirst du auf die Startseite des jeweiligen Landes gebracht",
  "us": "USA",
  "the us": "USA",
  "uk": "Großbritannien",
  "the uk": "Großbritannien",
  "fr": "Frankreich",
  "de": "Deutschland",
  "eu": "Europa",
  "sg": "Singapur",
  "my": "Malaysia",
  "th": "Thailand",
  "id": "Indonesien",
  "Country preferences": "Landeseinstellungen",
  "ACCEPT AND CLOSE": "ANNEHMEN UND SCHLIESSEN",
  "here": "hier mehr",
  "We use cookies to give you the best experience possible. Click accept to continue shopping or find out more in our cookie policy": "Wir verwenden Cookies um dir die beste Funktionalität zu ermöglichen. Klicke akzeptieren um weiter zu shoppen oder erfahre",
  "privacyNoticeSignUpGuestCheckbox" : "Mit dem Klicken dieser Box stimmst du zu, personalisierte Marketing E-Mails zu erhalten und bestätigst, dass du mindestens 16 Jahre alt bist. Wir bearbeiten deine Informationen im Einklang mit unseren ",
  "privacyNoticeUrlTextSignUpGuestCheckbox" : "Datenschutzrichtlinien",
  "privacyNoticeBeforeLink": "Ich bin damit einverstanden, personalisierte Marketing-E-Mails zu erhalten und bestätige, dass ich mindestens 16 Jahre alt bin. Wir werden Ihre Daten in Übereinstimmung mit unserer ",
  "privacyNoticeUrlText": "Datenschutzerklärung verarbeiten",
  "You have reached the limit of products allowed in your Wishlist. To add more products, please delete items from your list.": "Deine Wunschliste ist voll. Entferne einige Produkte, bevor du neue hinzufügst.",
  "Your Wishlist is full. To add more, you will need to remove some products.": "Deine Wunschliste ist voll. Entferne einige Produkte, bevor du neue hinzufügst.",
  "change your shipping destination": "lieferadresse ändern",
  "Maximum characters is ${maxLengthName}" : "Maximal is ${maxLengthName} Zeichen",
  "START A RETURN": "STARTEN SIE EINE RÜCKGABE",
  "TRACK MY ORDER": "MEINE BESTELLUNG VERFOLGEN",
  "NOT YET DISPATCHED" : "NOCH NICHT VERSANDT",
  "Please remove special characters": "Bitte entfernen Sie Sonderzeichen",
  "Arriving by" : "Anreise mit",
  "Remaining items to be delivered": "Noch zu liefernde Artikel",
  "static map": "statische Karte",
  "Confirming your order...": "Bestellung bestätigen...",
  "Your order could not be completed": "Deine Bestellung konnte nicht abgeschlossen werden",
  "Use current location" : "Aktuellen Standort verwenden",
  "Current Location" : "Aktueller Standort",
  "Deliver to this address": "An diese Adresse schicken",
  "Displaying your last 20 orders." : "Deine 20 letzten Bestellungen",
  "Displaying your last 20 returns." : "Deine 20 letzten Rückgaben",
  "Need your full order history?" : "Deine komplette Bestellhistorie einsehen?",
  "Need your full return history?" : "Deine komplette Rückgabenhistorie einsehen?",
  " Contact customer service on" : "Kundenservice kontaktieren unter",
  "Looking to return an item?": "Ein Teil zurückgeben?",
  "View Orders & Start A Return": "Bestellungen ansehen & einen Umtausch starten",
  "Item not available": "Objekt nicht verfügbar",
  "Product Details": "Détails du produit",
  "SHOP ALL":"SHOPPER TOUS LES",
  "All" : "Alle",
  "Check password criteria.": "Überprüfen Sie die Passwortkriterien.",
  "Your password must contain:": "Ihr Passwort muss enthalten:",
  "8-20 characters": "8-20 Zeichen",
  "A lower case letter": "Einen Kleinbuchstaben",
  "An upper case letter": "Einen Großbuchstaben",
  "A number": "Eine Ziffer",
  "This site is protected by reCAPTCHA and the Google ${privacyLink} and ${termsLink} apply.": "Diese Website ist durch reCAPTCHA und Google geschützt ${privacyLink} und ${termsLink} anwenden.",
  "Recaptcha Terms of Service": "Agb",
  "Recaptcha Privacy Policy": "Datenschutz",
  "To a Store": "In ein Geschäft",
  "To a ParcelShop": "Zu einem ParcelShop",
  "To your chosen address": "An Ihre gewählte Adresse",
  "Delivery Method": "Versandart",
  "CANCEL": "STORNIEREN",
  "CHANGE": "VERÄNDERUNG",
  "Product currently unavailable": "Produkt momentan nicht verfügbar",
  "The transaction has not been authorized. It must be approved with PayPal before your order can proceed.": "Die Transaktion wurde nicht autorisiert. Es muss mit PayPal genehmigt werden, bevor Ihre Bestellung fortgesetzt werden kann.",
  "Use this address": "Diese Adresse verwenden",
  "To add a new address, you need to delete one from your list.": "Um eine neue Adresse hinzuzufügen, müssen Sie eine aus Ihrer Liste löschen."
}
